sdk/SmsSDK.py
sdk/__init__.py
sdk/algorithm.py
ronglian_sdk-0.8.dist-info/METADATA
ronglian_sdk-0.8.dist-info/WHEEL
ronglian_sdk-0.8.dist-info/top_level.txt
ronglian_sdk-0.8.dist-info/RECORD
