Metadata-Version: 2.1
Name: ronglian-sdk
Version: 0.8
Summary: RongLian SMS SDK
Home-page: https://github.com/cloopen/python-sms-sdk
Author: Panxd
Author-email: panxd@yuntongxun.com
License: UNKNOWN
Keywords: ronglian sms sdk
Platform: UNKNOWN
Classifier: Programming Language :: Python :: 3.6
Requires-Dist: requests
